{
"docusaurus/docs" : {
  "README" : ["README.md"],
  "ut" : ["ut.md"],
  "ut_annotated_object" : ["ut_annotated_object.md"],
  "ut_annotated_objects" : ["ut_annotated_objects.md"],
  "ut_annotation" : ["ut_annotation.md"],
  "ut_annotation_cache_manager" : ["ut_annotation_cache_manager.md"],
  "ut_annotation_manager" : ["ut_annotation_manager.md"],
  "ut_annotation_obj_cache_info" : ["ut_annotation_obj_cache_info.md"],
  "ut_annotation_objs_cache_info" : ["ut_annotation_objs_cache_info.md"],
  "ut_annotation_parser" : ["ut_annotation_parser.md"],
  "ut_annotations" : ["ut_annotations.md"],
  "ut_ansiconsole_helper" : ["ut_ansiconsole_helper.md"],
  "ut_be_between" : ["ut_be_between.md"],
  "ut_be_empty" : ["ut_be_empty.md"],
  "ut_be_false" : ["ut_be_false.md"],
  "ut_be_greater_or_equal" : ["ut_be_greater_or_equal.md"],
  "ut_be_greater_than" : ["ut_be_greater_than.md"],
  "ut_be_less_or_equal" : ["ut_be_less_or_equal.md"],
  "ut_be_less_than" : ["ut_be_less_than.md"],
  "ut_be_like" : ["ut_be_like.md"],
  "ut_be_not_null" : ["ut_be_not_null.md"],
  "ut_be_null" : ["ut_be_null.md"],
  "ut_be_true" : ["ut_be_true.md"],
  "ut_comparison_matcher" : ["ut_comparison_matcher.md"],
  "ut_compound_data_helper" : ["ut_compound_data_helper.md"],
  "ut_compound_data_value" : ["ut_compound_data_value.md"],
  "ut_console_reporter_base" : ["ut_console_reporter_base.md"],
  "ut_coverage" : ["ut_coverage.md"],
  "ut_coverage_block" : ["ut_coverage_block.md"],
  "ut_coverage_cobertura_reporter" : ["ut_coverage_cobertura_reporter.md"],
  "ut_coverage_helper" : ["ut_coverage_helper.md"],
  "ut_coverage_helper_block" : ["ut_coverage_helper_block.md"],
  "ut_coverage_helper_profiler" : ["ut_coverage_helper_profiler.md"],
  "ut_coverage_html_reporter" : ["ut_coverage_html_reporter.md"],
  "ut_coverage_options" : ["ut_coverage_options.md"],
  "ut_coverage_profiler" : ["ut_coverage_profiler.md"],
  "ut_coverage_report_html_helper" : ["ut_coverage_report_html_helper.md"],
  "ut_coverage_reporter_base" : ["ut_coverage_reporter_base.md"],
  "ut_coverage_sonar_reporter" : ["ut_coverage_sonar_reporter.md"],
  "ut_coveralls_reporter" : ["ut_coveralls_reporter.md"],
  "ut_curr_usr_compound_helper" : ["ut_curr_usr_compound_helper.md"],
  "ut_data_value" : ["ut_data_value.md"],
  "ut_data_value_anydata" : ["ut_data_value_anydata.md"],
  "ut_data_value_blob" : ["ut_data_value_blob.md"],
  "ut_data_value_boolean" : ["ut_data_value_boolean.md"],
  "ut_data_value_clob" : ["ut_data_value_clob.md"],
  "ut_data_value_collection" : ["ut_data_value_collection.md"],
  "ut_data_value_date" : ["ut_data_value_date.md"],
  "ut_data_value_dsinterval" : ["ut_data_value_dsinterval.md"],
  "ut_data_value_number" : ["ut_data_value_number.md"],
  "ut_data_value_object" : ["ut_data_value_object.md"],
  "ut_data_value_refcursor" : ["ut_data_value_refcursor.md"],
  "ut_data_value_timestamp" : ["ut_data_value_timestamp.md"],
  "ut_data_value_timestamp_ltz" : ["ut_data_value_timestamp_ltz.md"],
  "ut_data_value_timestamp_tz" : ["ut_data_value_timestamp_tz.md"],
  "ut_data_value_varchar2" : ["ut_data_value_varchar2.md"],
  "ut_data_value_xmltype" : ["ut_data_value_xmltype.md"],
  "ut_data_value_yminterval" : ["ut_data_value_yminterval.md"],
  "ut_documentation_reporter" : ["ut_documentation_reporter.md"],
  "ut_equal" : ["ut_equal.md"],
  "ut_event_item" : ["ut_event_item.md"],
  "ut_event_listener" : ["ut_event_listener.md"],
  "ut_event_manager" : ["ut_event_manager.md"],
  "ut_executable" : ["ut_executable.md"],
  "ut_executable_test" : ["ut_executable_test.md"],
  "ut_executables" : ["ut_executables.md"],
  "ut_expectation" : ["ut_expectation.md"],
  "ut_expectation_compound" : ["ut_expectation_compound.md"],
  "ut_expectation_processor" : ["ut_expectation_processor.md"],
  "ut_expectation_result" : ["ut_expectation_result.md"],
  "ut_expectation_results" : ["ut_expectation_results.md"],
  "ut_file_mapper" : ["ut_file_mapper.md"],
  "ut_file_mapping" : ["ut_file_mapping.md"],
  "ut_file_mappings" : ["ut_file_mappings.md"],
  "ut_have_count" : ["ut_have_count.md"],
  "ut_integer_list" : ["ut_integer_list.md"],
  "ut_junit_reporter" : ["ut_junit_reporter.md"],
  "ut_key_anyval_pair" : ["ut_key_anyval_pair.md"],
  "ut_key_anyval_pairs" : ["ut_key_anyval_pairs.md"],
  "ut_key_value_pair" : ["ut_key_value_pair.md"],
  "ut_key_value_pairs" : ["ut_key_value_pairs.md"],
  "ut_logical_suite" : ["ut_logical_suite.md"],
  "ut_match" : ["ut_match.md"],
  "ut_matcher" : ["ut_matcher.md"],
  "ut_metadata" : ["ut_metadata.md"],
  "ut_object_name" : ["ut_object_name.md"],
  "ut_object_names" : ["ut_object_names.md"],
  "ut_output_buffer_base" : ["ut_output_buffer_base.md"],
  "ut_output_reporter_base" : ["ut_output_reporter_base.md"],
  "ut_output_table_buffer" : ["ut_output_table_buffer.md"],
  "ut_reporter_base" : ["ut_reporter_base.md"],
  "ut_reporters" : ["ut_reporters.md"],
  "ut_results_counter" : ["ut_results_counter.md"],
  "ut_run" : ["ut_run.md"],
  "ut_runner" : ["ut_runner.md"],
  "ut_sonar_test_reporter" : ["ut_sonar_test_reporter.md"],
  "ut_suite" : ["ut_suite.md"],
  "ut_suite_builder" : ["ut_suite_builder.md"],
  "ut_suite_item" : ["ut_suite_item.md"],
  "ut_suite_items" : ["ut_suite_items.md"],
  "ut_suite_manager" : ["ut_suite_manager.md"],
  "ut_teamcity_reporter" : ["ut_teamcity_reporter.md"],
  "ut_teamcity_reporter_helper" : ["ut_teamcity_reporter_helper.md"],
  "ut_test" : ["ut_test.md"],
  "ut_tfs_junit_reporter" : ["ut_tfs_junit_reporter.md"],
  "ut_utils" : ["ut_utils.md"],
  "ut_varchar2_list" : ["ut_varchar2_list.md"],
  "ut_varchar2_rows" : ["ut_varchar2_rows.md"],
  "ut_xunit_reporter" : ["ut_xunit_reporter.md"]
}
}
